tapisservice/__init__.py
tapisservice/auth.py
tapisservice/config.py
tapisservice/configschema.json
tapisservice/errors.py
tapisservice/logs.py
tapisservice/tapisdjango/__init__.py
tapisservice/tapisfastapi/__init__.py
tapisservice/tapisfastapi/auth.py
tapisservice/tapisfastapi/utils.py
tapisservice/tapisflask/__init__.py
tapisservice/tapisflask/auth.py
tapisservice/tapisflask/resources.py
tapisservice/tapisflask/utils.py
tapisservice/tenants.py
tapisservice/utils.py
tapisservice-1.9.0.dist-info/METADATA
tapisservice-1.9.0.dist-info/WHEEL
tapisservice-1.9.0.dist-info/RECORD
