Metadata-Version: 2.3
Name: tapisservice
Version: 1.9.0
Summary: Python lib for interacting with an instance of the Tapis API Framework's tapisservice plugin.
License: BSD-4-Clause
Author: Joe Stubbs
Author-email: jstubbs@tacc.utexas.edu
Maintainer: Joe Stubbs
Maintainer-email: jstubbs@tacc.utexas.edu
Requires-Python: >=3.8,<4.0
Classifier: License :: Other/Proprietary License
Classifier: Programming Language :: Python :: 3
Classifier: Programming Language :: Python :: 3.8
Classifier: Programming Language :: Python :: 3.9
Classifier: Programming Language :: Python :: 3.10
Classifier: Programming Language :: Python :: 3.11
Classifier: Programming Language :: Python :: 3.12
Classifier: Programming Language :: Python :: 3.13
Requires-Dist: pycryptodome (>=3.6.0)
Requires-Dist: tapipy (>=1.9.0)
Project-URL: Repository, https://github.com/tapis-project/tapipy-tapisservice
